pynox/__init__.py
pynox/find_area.py
pynox-1.0.1.dist-info/METADATA
pynox-1.0.1.dist-info/WHEEL
pynox-1.0.1.dist-info/top_level.txt
pynox-1.0.1.dist-info/RECORD
