Metadata-Version: 2.1
Name: pynox
Version: 1.0.1
Summary: Test
Home-page: UNKNOWN
Author: Ninenox
Author-email: nisit15@hotmail.com
License: MIT
Platform: UNKNOWN
Requires-Dist: numpy
